{
  "cluster": "E",
  "theme": "Creator & Media Intelligence",
  "dispatched_at": "2026-04-16",
  "last_update": "2026-04-17T08:30:00Z",
  "status": "9/11 merged, 2 in-flight",
  "apps": {
    "e1": {"id": "contentos", "sessionId": "702884044000508353", "port": 8130, "status": "merged"},
    "e2": {"id": "brandvoice", "sessionId": "4505720500122786990", "port": 8131, "status": "planning"},
    "e3": {"id": "videonarrator", "sessionId": "13882137444449305913", "port": 8132, "status": "planning"},
    "e4": {"id": "seointelligence", "sessionId": "8819174169243680979", "port": 8133, "status": "merged"},
    "e5": {"id": "ghostwriter", "sessionId": "1426445268679873553", "port": 8134, "status": "merged"},
    "e6": {"id": "socialintelligence", "sessionId": "1239505572246393993", "port": 8135, "status": "planning"},
    "e7": {"id": "creatoranalytics", "sessionId": "1685178805975000268", "port": 8136, "status": "merged"},
    "e8": {"id": "copyoptimizer", "sessionId": "6860208834653470720", "port": 8137, "status": "planning"},
    "e9": {"id": "localizationos", "sessionId": "14264148859996365504", "port": 8138, "status": "merged"},
    "e10": {"id": "podcastos", "sessionId": "797495855510318441", "port": 8139, "status": "failed"},
    "e11": {"id": "visualcontext", "sessionId": "11138961548351992294", "port": 8140, "status": "awaiting_user_feedback"}
  },
  "notes": "Cluster E foundation merged (E1, E4, E5, E7, E9). Planning sessions in progress (E2, E3, E6, E8). PodcastOS failed — needs investigation. VisualContext awaiting user feedback on jules.google.com."
}
